affinewarp/__init__.py
affinewarp/_optimizers.py
affinewarp/bmat.py
affinewarp/crossval.py
affinewarp/datasets.py
affinewarp/metrics.py
affinewarp/multiwarp.py
affinewarp/piecewisewarp.py
affinewarp/shiftwarp.py
affinewarp/spikedata.py
affinewarp/utils.py
affinewarp/visualization.py
affinewarp-0.2.0.dist-info/LICENSE
affinewarp-0.2.0.dist-info/METADATA
affinewarp-0.2.0.dist-info/WHEEL
affinewarp-0.2.0.dist-info/top_level.txt
affinewarp-0.2.0.dist-info/RECORD
