Metadata-Version: 2.1
Name: affinewarp
Version: 0.2.0
Summary: Code for time warping multi-dimensional time series.
Home-page: https://github.com/ahwillia/affinewarp
Author: Alex Williams
Author-email: Alex Williams <alex.h.williams@nyu.edu>, Niru Maheswaranathan <niru@hey.com>
License: MIT License
Project-URL: Homepage, https://github.com/ahwillia/affinewarp
Requires-Python: >=3.7
License-File: LICENSE
Requires-Dist: numpy >=1.19
Requires-Dist: scipy
Requires-Dist: matplotlib
Requires-Dist: numba
Requires-Dist: tqdm
Requires-Dist: scikit-learn
Requires-Dist: pytest
